{"stations": [{"scode":"16ABN138B","sname":"Cité 138 Logts","nbl":"2","stype":"bus","cid":"1644","cname":"Aïn Benian"},
{"scode":"16ABNAGCB","sname":"Aïn Benian (Station de bus)","nbl":"10","stype":"bus","cid":"1644","cname":"Aïn Benian"},
{"scode":"16ABNBDSB","sname":"C.E.M Abd-el-hamid Ben Badis","nbl":"2","stype":"bus","cid":"1644","cname":"Aïn Benian"},
{"scode":"16ABNBKKB","sname":"Cité Boukikaz Amar","nbl":"4","stype":"bus","cid":"1644","cname":"Aïn Benian"},
{"scode":"16ABNBLVB","sname":"Belvedère","nbl":"4","stype":"bus","cid":"1644","cname":"Aïn Benian"},
{"scode":"16ABNCHTB","sname":"Château BOUMEDIENE","nbl":"2","stype":"bus","cid":"1644","cname":"Aïn Benian"},
{"scode":"16ABNCIMB","sname":"Cimetiére","nbl":"4","stype":"bus","cid":"1644","cname":"Aïn Benian"},
{"scode":"16ABNCTRB","sname":"Ain Benian (Centre)","nbl":"2","stype":"bus","cid":"1644","cname":"Aïn Benian"},
{"scode":"16ABNFALB","sname":"Bainem - Les falaises -","nbl":"4","stype":"bus","cid":"1644","cname":"Aïn Benian"},
{"scode":"16ABNINTB","sname":"Intersection - Entrée Ain Benian -","nbl":"4","stype":"bus","cid":"1644","cname":"Aïn Benian"},
{"scode":"16ABNLPPB","sname":"COPEMAD","nbl":"2","stype":"bus","cid":"1644","cname":"Aïn Benian"},
{"scode":"16ABNMKTB","sname":"Marché de Ain Benian","nbl":"2","stype":"bus","cid":"1644","cname":"Aïn Benian"},
{"scode":"16ABNOBMB","sname":"Oued Beni Messous","nbl":"2","stype":"bus","cid":"1644","cname":"Aïn Benian"},
{"scode":"16ABNPHRB","sname":"Le phare","nbl":"4","stype":"bus","cid":"1644","cname":"Aïn Benian"},
{"scode":"16ABNPLTB","sname":"Plateau de Ain Benian","nbl":"2","stype":"bus","cid":"1644","cname":"Aïn Benian"},
{"scode":"16ABNROCB","sname":"Grand Rocher","nbl":"4","stype":"bus","cid":"1644","cname":"Aïn Benian"},
{"scode":"16ABNROMB","sname":"Bains romains","nbl":"4","stype":"bus","cid":"1644","cname":"Aïn Benian"},
{"scode":"16ABNTAMB","sname":"Les Tamaris","nbl":"4","stype":"bus","cid":"1644","cname":"Aïn Benian"},
{"scode":"16ACHAGCB","sname":"El Achour (Station de bus)","nbl":"8","stype":"bus","cid":"1652","cname":"El Achour"},
{"scode":"16ACHAVGB","sname":"El-Achour - Ecole des aveugles -","nbl":"2","stype":"bus","cid":"1652","cname":"El Achour"},
{"scode":"16ACHNPSB","sname":"ONPS","nbl":"1","stype":"bus","cid":"1652","cname":"El Achour"},
{"scode":"16ACHOR1B","sname":"Oued Romane","nbl":"2","stype":"bus","cid":"1652","cname":"El Achour"},
{"scode":"16ACHSAHB","sname":"Résidence SAHRAOUI","nbl":"1","stype":"bus","cid":"1652","cname":"El Achour"},
{"scode":"16BBHCTRB","sname":"Baba Hassen","nbl":"2","stype":"bus","cid":"1655","cname":"Baba Hassen"},
{"scode":"16BBHNSRB","sname":"Baba Hassen - Place En-Nasr -","nbl":"2","stype":"bus","cid":"1655","cname":"Baba Hassen"},
{"scode":"16BBHPEPB","sname":"La pépinière","nbl":"2","stype":"bus","cid":"1655","cname":"Baba Hassen"},
{"scode":"16BCHAR1B","sname":"Bouchaoui - Autoroute","nbl":"2","stype":"bus","cid":"1650","cname":"Cheraga"},
{"scode":"16BCHCLIB","sname":"Bouchaoui - Polyclinique -","nbl":"4","stype":"bus","cid":"1650","cname":"Cheraga"},
{"scode":"16BCHCNRB","sname":"Bouchaoui - CNR","nbl":"2","stype":"bus","cid":"1650","cname":"Cheraga"},
{"scode":"16BCHFERB","sname":"Bouchaoui - Ecole Mouloud Feraoun -","nbl":"2","stype":"bus","cid":"1650","cname":"Cheraga"},
{"scode":"16BCHMOSB","sname":"Bouchaoui - Mosquée","nbl":"4","stype":"bus","cid":"1650","cname":"Cheraga"},
{"scode":"16BCHOUTB","sname":"Sortie Bouchaoui","nbl":"4","stype":"bus","cid":"1650","cname":"Cheraga"},
{"scode":"16BEB411B","sname":"Cité 411 logts","nbl":"2","stype":"bus","cid":"1639","cname":"Bordj El Bahri"},
{"scode":"16BEBBZNB","sname":"Douar Ben Ziane","nbl":"6","stype":"bus","cid":"1639","cname":"Bordj El Bahri"},
{"scode":"16BEBCG1B","sname":"Café Chergui","nbl":"4","stype":"bus","cid":"1639","cname":"Bordj El Bahri"},
{"scode":"16BEBCHGB","sname":"Café Chergui (Station de bus)","nbl":"10","stype":"bus","cid":"1639","cname":"Bordj El Bahri"},
{"scode":"16BEBCHGT","sname":"Café Chergui","nbl":"2","stype":"tramway","cid":"1639","cname":"Bordj El Bahri"},
{"scode":"16BEBSSHB","sname":"Station Services Harraga","nbl":"6","stype":"bus","cid":"1639","cname":"Bordj El Bahri"},
{"scode":"16BEBZGAB","sname":"Ben Zerga","nbl":"6","stype":"bus","cid":"1639","cname":"Bordj El Bahri"},
{"scode":"16BEKCLIT","sname":"Bordj El Kiffan - Polyclinique","nbl":"2","stype":"tramway","cid":"1630","cname":"Bordj El Kiffan"},
{"scode":"16BEKCLMT","sname":"Clair Matin","nbl":"2","stype":"tramway","cid":"1630","cname":"Bordj El Kiffan"},
{"scode":"16BEKCTRT","sname":"Bordj El Kiffan - Centre","nbl":"2","stype":"tramway","cid":"1630","cname":"Bordj El Kiffan"},
{"scode":"16BEKDIPB","sname":"Lycée diplomatique de Dergana","nbl":"8","stype":"bus","cid":"1630","cname":"Bordj El Kiffan"},
{"scode":"16BEKDRST","sname":"Sidi Dris","nbl":"2","stype":"tramway","cid":"1630","cname":"Bordj El Kiffan"},
{"scode":"16BEKLYCT","sname":"Bordj El Kiffan - Lycée","nbl":"2","stype":"tramway","cid":"1630","cname":"Bordj El Kiffan"},
{"scode":"16BEKMBTT","sname":"Ben Merabet","nbl":"2","stype":"tramway","cid":"1630","cname":"Bordj El Kiffan"},
{"scode":"16BEKMHST","sname":"Mouhous موحوس","nbl":"2","stype":"tramway","cid":"1630","cname":"Bordj El Kiffan"},
{"scode":"16BEKMIMT","sname":"Mimouni Hamoud","nbl":"2","stype":"tramway","cid":"1630","cname":"Bordj El Kiffan"},
{"scode":"16BEKMRDT","sname":"Ben Mered","nbl":"2","stype":"tramway","cid":"1630","cname":"Bordj El Kiffan"},
{"scode":"16BEKREDT","sname":"Ben Redouane","nbl":"2","stype":"tramway","cid":"1630","cname":"Bordj El Kiffan"},
{"scode":"16BEKZRGT","sname":"Benzergua","nbl":"2","stype":"tramway","cid":"1630","cname":"Bordj El Kiffan"},
{"scode":"16BENIMSB","sname":"Benimessous","nbl":"6","stype":"bus","cid":"1632","cname":"Beni Messous"},
{"scode":"16BEOBASB","sname":"Basta Ali","nbl":"2","stype":"bus","cid":"1605","cname":"Bab El Oued"},
{"scode":"16BEOBMRB","sname":"Bd MIRA","nbl":"4","stype":"bus","cid":"1605","cname":"Bab El Oued"},
{"scode":"16BEOCTRB","sname":"Bab el oued","nbl":"4","stype":"bus","cid":"1605","cname":"Bab El Oued"},
{"scode":"16BEOFERB","sname":"Stade Ferhani","nbl":"10","stype":"bus","cid":"1605","cname":"Bab El Oued"},
{"scode":"16BEOKETB","sname":"El Kettani","nbl":"7","stype":"bus","cid":"1605","cname":"Bab El Oued"},
{"scode":"16BEOMIRB","sname":"Miramar","nbl":"4","stype":"bus","cid":"1605","cname":"Bab El Oued"},
{"scode":"16BEOOKBB","sname":"Okba (Lycée)","nbl":"6","stype":"bus","cid":"1605","cname":"Bab El Oued"},
{"scode":"16BEOSQRB","sname":"Square Port Said","nbl":"17","stype":"bus","cid":"1605","cname":"Bab El Oued"},
{"scode":"16BEOTLBB","sname":"Bd Abderrahmane TALEB","nbl":"2","stype":"bus","cid":"1605","cname":"Bab El Oued"},
{"scode":"16BEZ19MB","sname":"19 Mai (Cité universitaire)","nbl":"1","stype":"bus","cid":"1621","cname":"Bab Ezzouar"},
{"scode":"16BEZ5JLT","sname":"Cité 5 juillet","nbl":"2","stype":"tramway","cid":"1621","cname":"Bab Ezzouar"},
{"scode":"16BEZ845T","sname":"Cité 08 Mai 1945","nbl":"2","stype":"tramway","cid":"1621","cname":"Bab Ezzouar"},
{"scode":"16BEZALIB","sname":"El-Alia (Cité universitaire)","nbl":"2","stype":"bus","cid":"1621","cname":"Bab Ezzouar"},
{"scode":"16BEZBRGB","sname":"Barrage de l'université","nbl":"2","stype":"bus","cid":"1621","cname":"Bab Ezzouar"},
{"scode":"16BEZCTRB","sname":"Bab Ezzouar (Centre)","nbl":"22","stype":"bus","cid":"1621","cname":"Bab Ezzouar"},
{"scode":"16BEZCTRT","sname":"Bab Ezzouar - le Pont","nbl":"2","stype":"tramway","cid":"1621","cname":"Bab Ezzouar"},
{"scode":"16BEZCU1T","sname":"Cité Universitaire - CUB 1","nbl":"2","stype":"tramway","cid":"1621","cname":"Bab Ezzouar"},
{"scode":"16BEZCU3B","sname":"Rabia Tahar (CUB3)","nbl":"1","stype":"bus","cid":"1621","cname":"Bab Ezzouar"},
{"scode":"16BEZHTLB","sname":"Les hôtels","nbl":"2","stype":"bus","cid":"1621","cname":"Bab Ezzouar"},
{"scode":"16BEZJRFB","sname":"El-Djorf","nbl":"2","stype":"bus","cid":"1621","cname":"Bab Ezzouar"},
{"scode":"16BEZMOSB","sname":"Mousalaha (Cité 5 Juillet)","nbl":"13","stype":"bus","cid":"1621","cname":"Bab Ezzouar"},
{"scode":"16BEZPC1B","sname":"DG Protection civile","nbl":"4","stype":"bus","cid":"1621","cname":"Bab Ezzouar"},
{"scode":"16BEZSEFB","sname":"Souk el fellah","nbl":"24","stype":"bus","cid":"1621","cname":"Bab Ezzouar"},
{"scode":"16BEZSEFT","sname":"Cité Rabia","nbl":"2","stype":"tramway","cid":"1621","cname":"Bab Ezzouar"},
{"scode":"16BEZSMMB","sname":"Soumam","nbl":"12","stype":"bus","cid":"1621","cname":"Bab Ezzouar"},
{"scode":"16BEZSURB","sname":"Sureté de wilaya","nbl":"2","stype":"bus","cid":"1621","cname":"Bab Ezzouar"},
{"scode":"16BEZTTOB","sname":"Parc Tito","nbl":"2","stype":"bus","cid":"1621","cname":"Bab Ezzouar"},
{"scode":"16BEZUNIT","sname":"Université de Bab Ezzouar","nbl":"2","stype":"tramway","cid":"1621","cname":"Bab Ezzouar"},
{"scode":"16BEZUSTB","sname":"U.S.T.H.B","nbl":"1","stype":"bus","cid":"1621","cname":"Bab Ezzouar"},
{"scode":"16BEZYEFB","sname":"Ismaïl Yefsah","nbl":"2","stype":"bus","cid":"1621","cname":"Bab Ezzouar"},
{"scode":"16BGN2MLB","sname":"Deux moulins","nbl":"4","stype":"bus","cid":"1606","cname":"Bologhine"},
{"scode":"16BGNAPCB","sname":"Siége APC Bologhine","nbl":"4","stype":"bus","cid":"1606","cname":"Bologhine"},
{"scode":"16BGNCTRB","sname":"Stade Bologhine","nbl":"8","stype":"bus","cid":"1606","cname":"Bologhine"},
{"scode":"16BGNCTRL","sname":"Téléphérique Bologhine","nbl":"2","stype":"Téléphérique","cid":"1606","cname":"Bologhine"},
{"scode":"16BGNDAML","sname":"Notre-Dame d'Afrique","nbl":"2","stype":"Téléphérique","cid":"1606","cname":"Bologhine"},
{"scode":"16BGNPLTB","sname":"Plateau de Bologhine","nbl":"4","stype":"bus","cid":"1606","cname":"Bologhine"},
{"scode":"16BIARCCB","sname":"El-Biar (Centre)","nbl":"8","stype":"bus","cid":"1610","cname":"El Biar"},
{"scode":"16BKD005B","sname":"Banque","nbl":"6","stype":"bus","cid":"1612","cname":"Birkhadem"},
{"scode":"16BKD006B","sname":"Lavage","nbl":"6","stype":"bus","cid":"1612","cname":"Birkhadem"},
{"scode":"16BKDAGCB","sname":"Birkhadem (Station de bus)","nbl":"15","stype":"bus","cid":"1612","cname":"Birkhadem"},
{"scode":"16BKDMCTB","sname":"Birkhadem (Centre)","nbl":"10","stype":"bus","cid":"1612","cname":"Birkhadem"},
{"scode":"16BKDONLB","sname":"Les vergers 2 \/ Onalait","nbl":"3","stype":"bus","cid":"1612","cname":"Birkhadem"},
{"scode":"16BKDSCLB","sname":"Sorecal","nbl":"6","stype":"bus","cid":"1612","cname":"Birkhadem"},
{"scode":"16BKDSMBB","sname":"Sidi Mbarek, Birkhadem","nbl":"6","stype":"bus","cid":"1612","cname":"Birkhadem"},
{"scode":"16BKDSTDB","sname":"Stade","nbl":"4","stype":"bus","cid":"1612","cname":"Birkhadem"},
{"scode":"16BKDSTPB","sname":"Carrefour Djnane Sfari \/ Stop","nbl":"3","stype":"bus","cid":"1612","cname":"Birkhadem"},
{"scode":"16BKDVG1B","sname":"Les vergers 1","nbl":"3","stype":"bus","cid":"1612","cname":"Birkhadem"},
{"scode":"16BMRCRDB","sname":"Concorde","nbl":"7","stype":"bus","cid":"1609","cname":"Bir Mourad Raïs"},
{"scode":"16BMRCT1B","sname":"La Côte","nbl":"12","stype":"bus","cid":"1609","cname":"Bir Mourad Raïs"},
{"scode":"16BMRCTRB","sname":"Bir Mourad Rais (Centre)","nbl":"24","stype":"bus","cid":"1609","cname":"Bir Mourad Raïs"},
{"scode":"16BMRJASB","sname":"Les Jasmins","nbl":"4","stype":"bus","cid":"1609","cname":"Bir Mourad Raïs"},
{"scode":"16BMRSC1B","sname":"Les sources (Ravin)","nbl":"4","stype":"bus","cid":"1609","cname":"Bir Mourad Raïs"},
{"scode":"16BMRSIGB","sname":"Stade Mohamed Iguer","nbl":"4","stype":"bus","cid":"1609","cname":"Bir Mourad Raïs"},
{"scode":"16BMTADLB","sname":"Cité AADL Boumaati","nbl":"3","stype":"bus","cid":"1613","cname":"El Harrach"},
{"scode":"16BNAKCUB","sname":"Benaknoun (Cité Universitaire)","nbl":"6","stype":"bus","cid":"1622","cname":"Ben Aknoun"},
{"scode":"16BNKAGCB","sname":"Benaknoun (Station de bus)","nbl":"24","stype":"bus","cid":"1622","cname":"Ben Aknoun"},
{"scode":"16BNKCU2B","sname":"Cité Universitaire Taleb Abderrahmane","nbl":"2","stype":"bus","cid":"1622","cname":"Ben Aknoun"},
{"scode":"16BNKLNGB","sname":"Fac des langues","nbl":"2","stype":"bus","cid":"1622","cname":"Ben Aknoun"},
{"scode":"16BNKMDFB","sname":"Ministére des finances","nbl":"2","stype":"bus","cid":"1622","cname":"Ben Aknoun"},
{"scode":"16BNKMLKB","sname":"Cité Malki","nbl":"1","stype":"bus","cid":"1622","cname":"Ben Aknoun"},
{"scode":"16BNKMOKB","sname":"Lycée El-Mokrani","nbl":"6","stype":"bus","cid":"1622","cname":"Ben Aknoun"},
{"scode":"16BNKTFCB","sname":"ITFC","nbl":"1","stype":"bus","cid":"1622","cname":"Ben Aknoun"},
{"scode":"16BNMAR1B","sname":"Cercle National de l'armée 1","nbl":"6","stype":"bus","cid":"1632","cname":"Beni Messous"},
{"scode":"16BNMAR2B","sname":"Cercle National de l'armée 2","nbl":"6","stype":"bus","cid":"1632","cname":"Beni Messous"},
{"scode":"16BNMSMHB","sname":"Bousmaha","nbl":"2","stype":"bus","cid":"1632","cname":"Beni Messous"},
{"scode":"16BNMSY1B","sname":"Entrée de Sidi Youcef","nbl":"2","stype":"bus","cid":"1632","cname":"Beni Messous"},
{"scode":"16BNMSY2B","sname":"Station de bus de Sidi Youcef (AADL)","nbl":"2","stype":"bus","cid":"1632","cname":"Beni Messous"},
{"scode":"16BOUCHAB","sname":"Bouchaoui","nbl":"2","stype":"bus","cid":"1650","cname":"Cheraga"},
{"scode":"16BRBBSLB","sname":"Boubsila","nbl":"9","stype":"bus","cid":"1619","cname":"Bourouba"},
{"scode":"16BRBCIMB","sname":"Bourouba (Cimetiére)","nbl":"8","stype":"bus","cid":"1619","cname":"Bourouba"},
{"scode":"16BRBEAUB","sname":"Bourouba (Station de Taxis)","nbl":"9","stype":"bus","cid":"1619","cname":"Bourouba"},
{"scode":"16BRCHBLB","sname":"Cheval Blanc","nbl":"2","stype":"bus","cid":"1610","cname":"El Biar"},
{"scode":"16BREMP1B","sname":"Fort l'empereur","nbl":"4","stype":"bus","cid":"1610","cname":"El Biar"},
{"scode":"16BRK2K4B","sname":"Intersection 2004 logts Baraki","nbl":"2","stype":"bus","cid":"1614","cname":"Baraki"},
{"scode":"16BRKAGCB","sname":"Gare routiére de Baraki","nbl":"20","stype":"bus","cid":"1614","cname":"Baraki"},
{"scode":"16BRKBGZB","sname":"Benghazi","nbl":"4","stype":"bus","cid":"1614","cname":"Baraki"},
{"scode":"16BRKBIBB","sname":"Mosquée Bachir El-Ibrahimi","nbl":"2","stype":"bus","cid":"1614","cname":"Baraki"},
{"scode":"16BRKCMHB","sname":"Cité Mahmoudi","nbl":"1","stype":"bus","cid":"1614","cname":"Baraki"},
{"scode":"16BRKCTRB","sname":"Baraki (Centre)","nbl":"6","stype":"bus","cid":"1614","cname":"Baraki"},
{"scode":"16BRKEBKB","sname":"Ecole Ahmed Benkhoudja","nbl":"2","stype":"bus","cid":"1614","cname":"Baraki"},
{"scode":"16BRKFOYB","sname":"Foyer","nbl":"12","stype":"bus","cid":"1614","cname":"Baraki"},
{"scode":"16BRKHMHB","sname":"Rond Point Haouch Mihoub","nbl":"2","stype":"bus","cid":"1614","cname":"Baraki"},
{"scode":"16BRKMBGB","sname":"Mosquée Omar Ibn Al-Khattab (Benghazi)","nbl":"6","stype":"bus","cid":"1614","cname":"Baraki"},
{"scode":"16BRKMR1B","sname":"Laamirat Baraki","nbl":"2","stype":"bus","cid":"1614","cname":"Baraki"},
{"scode":"16BRKREZB","sname":"Cimetière Sidi Rezine","nbl":"6","stype":"bus","cid":"1614","cname":"Baraki"},
{"scode":"16BRKRPTB","sname":"Salle de judo Taher NAZEF","nbl":"2","stype":"bus","cid":"1614","cname":"Baraki"},
{"scode":"16BRKSLXB","sname":"Hôtel Soluxe","nbl":"10","stype":"bus","cid":"1614","cname":"Baraki"},
{"scode":"16BRKSOBB","sname":"SOBEMAFE","nbl":"6","stype":"bus","cid":"1614","cname":"Baraki"},
{"scode":"16BRKSTDB","sname":"Stade Olympique de Baraki","nbl":"6","stype":"bus","cid":"1614","cname":"Baraki"},
{"scode":"16BRNEUFB","sname":"Château neuf","nbl":"2","stype":"bus","cid":"1610","cname":"El Biar"},
{"scode":"16BRPINSB","sname":"El Biar - Les pins -","nbl":"2","stype":"bus","cid":"1610","cname":"El Biar"},
{"scode":"16BRRAPHB","sname":"St Raphael","nbl":"4","stype":"bus","cid":"1610","cname":"El Biar"},
{"scode":"16BRSCALB","sname":"Scala","nbl":"4","stype":"bus","cid":"1610","cname":"El Biar"},
{"scode":"16BRSTD1B","sname":"Stade El Biar","nbl":"2","stype":"bus","cid":"1610","cname":"El Biar"},
{"scode":"16BRTADLB","sname":"Cité AADL de Birtouta","nbl":"2","stype":"bus","cid":"1634","cname":"Birtouta"},
{"scode":"16BRTOSMB","sname":"Ouled Sidi M'hamed","nbl":"6","stype":"bus","cid":"1634","cname":"Birtouta"},
{"scode":"16BTACCBB","sname":"Carrefour Cité Bouhadja","nbl":"2","stype":"bus","cid":"1634","cname":"Birtouta"},
{"scode":"16BTAHDJB","sname":"Haouch El-Hadj","nbl":"2","stype":"bus","cid":"1634","cname":"Birtouta"},
{"scode":"16BTTAG1B","sname":"Birtouta (Station de bus)","nbl":"4","stype":"bus","cid":"1634","cname":"Birtouta"},
{"scode":"16BTTCFPB","sname":"Birtouta - CFPA -","nbl":"8","stype":"bus","cid":"1634","cname":"Birtouta"},
{"scode":"16BTTCKHB","sname":"Cité Sidi Lakhder","nbl":"2","stype":"bus","cid":"1634","cname":"Birtouta"},
{"scode":"16BTTEN1B","sname":"Birtouta (entrée Est)","nbl":"4","stype":"bus","cid":"1634","cname":"Birtouta"},
{"scode":"16BTTMNRB","sname":"Mosquée En-nour","nbl":"2","stype":"bus","cid":"1634","cname":"Birtouta"},
{"scode":"16BZDAN1B","sname":"El Anasser 1","nbl":"4","stype":"bus","cid":"1604","cname":"Belouizdad"},
{"scode":"16BZDAT1B","sname":"Les ateliers","nbl":"6","stype":"bus","cid":"1604","cname":"Belouizdad"},
{"scode":"16BZDATLB","sname":"Les ateliers - Avenue ALN -","nbl":"25","stype":"bus","cid":"1604","cname":"Belouizdad"},
{"scode":"16BZDDC1B","sname":"Place 11 décembre 1960","nbl":"4","stype":"bus","cid":"1604","cname":"Belouizdad"},
{"scode":"16BZDHALB","sname":"Les Halles","nbl":"7","stype":"bus","cid":"1604","cname":"Belouizdad"},
{"scode":"16BZDHB1B","sname":"Hamoud Boualem","nbl":"7","stype":"bus","cid":"1604","cname":"Belouizdad"},
{"scode":"16BZDHMAB","sname":"El Hamma","nbl":"4","stype":"bus","cid":"1604","cname":"Belouizdad"},
{"scode":"16BZDHMAL","sname":"Téléphérique Hamma","nbl":"2","stype":"Téléphérique","cid":"1604","cname":"Belouizdad"},
{"scode":"16BZDHMAM","sname":"Hamma","nbl":"2","stype":"metro","cid":"1604","cname":"Belouizdad"},
{"scode":"16BZDIDRB","sname":"Aissat Idir","nbl":"20","stype":"bus","cid":"1604","cname":"Belouizdad"},
{"scode":"16BZDIDRM","sname":"Aissat Idir","nbl":"2","stype":"metro","cid":"1604","cname":"Belouizdad"},
{"scode":"16BZDJRDB","sname":"Jardin d'essai","nbl":"10","stype":"bus","cid":"1604","cname":"Belouizdad"},
{"scode":"16BZDJRDL","sname":"Jardin d'essai","nbl":"2","stype":"Téléphérique","cid":"1604","cname":"Belouizdad"},
{"scode":"16BZDJRDM","sname":"Jardin d'essai","nbl":"2","stype":"metro","cid":"1604","cname":"Belouizdad"},
{"scode":"16BZDMUSB","sname":"Musset","nbl":"4","stype":"bus","cid":"1604","cname":"Belouizdad"},
{"scode":"16BZDSMHB","sname":"Sidi M'hamed","nbl":"4","stype":"bus","cid":"1604","cname":"Belouizdad"},
{"scode":"16BZH4SSB","sname":"Quatre saisons","nbl":"2","stype":"bus","cid":"1611","cname":"Bouzareah"},
{"scode":"16BZHAGCB","sname":"Bouzareah","nbl":"10","stype":"bus","cid":"1611","cname":"Bouzareah"},
{"scode":"16BZHALIB","sname":"Dar el-Alia","nbl":"2","stype":"bus","cid":"1611","cname":"Bouzareah"},
{"scode":"16BZHBHMB","sname":"Cité Bouhmam \/ Stade","nbl":"2","stype":"bus","cid":"1611","cname":"Bouzareah"},
{"scode":"16BZHBLNB","sname":"La cité blanche","nbl":"2","stype":"bus","cid":"1611","cname":"Bouzareah"},
{"scode":"16BZHBRNB","sname":"Baranès","nbl":"2","stype":"bus","cid":"1611","cname":"Bouzareah"},
{"scode":"16BZHBRRB","sname":"La Bruyére","nbl":"2","stype":"bus","cid":"1611","cname":"Bouzareah"},
{"scode":"16BZHBSKB","sname":"Bouskour","nbl":"2","stype":"bus","cid":"1611","cname":"Bouzareah"},
{"scode":"16BZHCH2B","sname":"Chevalley (vers Bouzareah)","nbl":"6","stype":"bus","cid":"1611","cname":"Bouzareah"},
{"scode":"16BZHCHBB","sname":"Chaaba","nbl":"2","stype":"bus","cid":"1611","cname":"Bouzareah"},
{"scode":"16BZHCRNB","sname":"Carnot","nbl":"2","stype":"bus","cid":"1611","cname":"Bouzareah"},
{"scode":"16BZHFV1B","sname":"Frais Vallon","nbl":"2","stype":"bus","cid":"1611","cname":"Bouzareah"},
{"scode":"16BZHFVSB","sname":"Frais Vallon - Sources","nbl":"2","stype":"bus","cid":"1611","cname":"Bouzareah"},
{"scode":"16BZHIDRB","sname":"El Idrissi","nbl":"2","stype":"bus","cid":"1611","cname":"Bouzareah"},
{"scode":"16BZHLMRB","sname":"Laamara","nbl":"2","stype":"bus","cid":"1611","cname":"Bouzareah"},
{"scode":"16BZHPTBB","sname":"Petits bois","nbl":"2","stype":"bus","cid":"1611","cname":"Bouzareah"},
{"scode":"16BZHRBRB","sname":"Robert","nbl":"2","stype":"bus","cid":"1611","cname":"Bouzareah"},
{"scode":"16BZHTDAB","sname":"Télédiffusion d'Algérie","nbl":"1","stype":"bus","cid":"1611","cname":"Bouzareah"},
{"scode":"16BZNREGB","sname":"La Regite","nbl":"1","stype":"bus","cid":"1604","cname":"Belouizdad"},
{"scode":"16CCAEROB","sname":"Aerohabitat","nbl":"1","stype":"bus","cid":"1601","cname":"Alger-Centre"},
{"scode":"16CCALIBM","sname":"Ali Boumendjel","nbl":"2","stype":"metro","cid":"1601","cname":"Alger-Centre"},
{"scode":"16CCART1B","sname":"Beaux arts","nbl":"4","stype":"bus","cid":"1601","cname":"Alger-Centre"},
{"scode":"16CCAUDNB","sname":"Place Audin","nbl":"6","stype":"bus","cid":"1601","cname":"Alger-Centre"},
{"scode":"16CCBEYRB","sname":"Parc de Beyrouth","nbl":"2","stype":"bus","cid":"1601","cname":"Alger-Centre"},
{"scode":"16CCCHMVB","sname":"Station 2 Mai \/ Ch-de-manoeuvre","nbl":"43","stype":"bus","cid":"1601","cname":"Alger-Centre"},
{"scode":"16CCDIDOB","sname":"Didouche Mourad","nbl":"2","stype":"bus","cid":"1601","cname":"Alger-Centre"},
{"scode":"16CCGEAYB","sname":"Place Geay","nbl":"1","stype":"bus","cid":"1601","cname":"Alger-Centre"},
{"scode":"16CCKBELB","sname":"Krim Belkacem","nbl":"2","stype":"bus","cid":"1601","cname":"Alger-Centre"},
{"scode":"16CCKHELM","sname":"Khelifa Boukhalfa","nbl":"2","stype":"metro","cid":"1601","cname":"Alger-Centre"},
{"scode":"16CCLZOMB","sname":"Lycée Zaineb Oum El-masakine","nbl":"2","stype":"bus","cid":"1601","cname":"Alger-Centre"},
{"scode":"16CCMECHB","sname":"Escalier mécanique","nbl":"2","stype":"bus","cid":"1601","cname":"Alger-Centre"},
{"scode":"16CCOUAGB","sname":"Stade Ouagnouni","nbl":"1","stype":"bus","cid":"1601","cname":"Alger-Centre"},
{"scode":"16CCPOSTB","sname":"Grande Poste","nbl":"21","stype":"bus","cid":"1601","cname":"Alger-Centre"},
{"scode":"16CCPOSTM","sname":"Grande Poste","nbl":"2","stype":"metro","cid":"1601","cname":"Alger-Centre"},
{"scode":"16CCSCCRB","sname":"Sacré coeur","nbl":"2","stype":"bus","cid":"1601","cname":"Alger-Centre"},
{"scode":"16CCSGDGB","sname":"Siége de Sonelgaz","nbl":"2","stype":"bus","cid":"1601","cname":"Alger-Centre"},
{"scode":"16CCTAG1B","sname":"Les Tagarins","nbl":"4","stype":"bus","cid":"1601","cname":"Alger-Centre"},
{"scode":"16CCTFACB","sname":"Tunnel des facultés","nbl":"1","stype":"bus","cid":"1601","cname":"Alger-Centre"},
{"scode":"16CCTIF1B","sname":"Parc Tifarti","nbl":"4","stype":"bus","cid":"1601","cname":"Alger-Centre"},
{"scode":"16CFGAGCB","sname":"Cheraga - Gare routiére -","nbl":"6","stype":"bus","cid":"1650","cname":"Cheraga"},
{"scode":"16CFGKRAB","sname":"El-Karia (Les dunes)","nbl":"6","stype":"bus","cid":"1650","cname":"Cheraga"},
{"scode":"16CFGSEFB","sname":"Souk el fellah - Cheraga -","nbl":"6","stype":"bus","cid":"1650","cname":"Cheraga"},
{"scode":"16CHEVALB","sname":"Chevalley (vers Cheraga)","nbl":"12","stype":"bus","cid":"1611","cname":"Bouzareah"},
{"scode":"16CHGHDDB","sname":"Hôtel Dar Diaf","nbl":"6","stype":"bus","cid":"1650","cname":"Cheraga"},
{"scode":"16CHGKMAB","sname":"El-Kerma","nbl":"6","stype":"bus","cid":"1650","cname":"Cheraga"},
{"scode":"16CHGRP1B","sname":"Rond-point de Cheraga","nbl":"2","stype":"bus","cid":"1650","cname":"Cheraga"},
{"scode":"16CRGAGCB","sname":"Gare routiére, Cheraga","nbl":"18","stype":"bus","cid":"1650","cname":"Cheraga"},
{"scode":"16CRGAMRB","sname":"Ammara","nbl":"2","stype":"bus","cid":"1650","cname":"Cheraga"},
{"scode":"16CRGLYCB","sname":"Lycée polyvalent","nbl":"2","stype":"bus","cid":"1650","cname":"Cheraga"},
{"scode":"16CRGQDSB","sname":"Al-Qods","nbl":"4","stype":"bus","cid":"1650","cname":"Cheraga"},
{"scode":"16CSDJDDB","sname":"Bab Djedid","nbl":"2","stype":"bus","cid":"1607","cname":"Casbah"},
{"scode":"16CSHAAIB","sname":"CHU Ait Ali Idir","nbl":"2","stype":"bus","cid":"1607","cname":"Casbah"},
{"scode":"16CSMARTB","sname":"Place des Martyrs","nbl":"24","stype":"bus","cid":"1607","cname":"Casbah"},
{"scode":"16CSMARTM","sname":"Place des Martyrs","nbl":"2","stype":"metro","cid":"1607","cname":"Casbah"},
{"scode":"16CSPECHB","sname":"La pêcherie","nbl":"2","stype":"bus","cid":"1607","cname":"Casbah"},
{"scode":"16CSSABDB","sname":"Sidi Abderrahmane","nbl":"2","stype":"bus","cid":"1607","cname":"Casbah"},
{"scode":"16DBRAKDB","sname":"Rue Ahmed Ouaked","nbl":"2","stype":"bus","cid":"1623","cname":"Dely Ibrahim"},
{"scode":"16DBRBINB","sname":"Hai el bina","nbl":"2","stype":"bus","cid":"1623","cname":"Dely Ibrahim"},
{"scode":"16DBRCARB","sname":"Bois des cars","nbl":"8","stype":"bus","cid":"1623","cname":"Dely Ibrahim"},
{"scode":"16DBRFAFB","sname":"Fédération de Football","nbl":"4","stype":"bus","cid":"1623","cname":"Dely Ibrahim"},
{"scode":"16DBRLAHB","sname":"Ain Allah","nbl":"8","stype":"bus","cid":"1623","cname":"Dely Ibrahim"},
{"scode":"16DBROPRB","sname":"Dely Brahim (Opera)","nbl":"4","stype":"bus","cid":"1623","cname":"Dely Ibrahim"},
{"scode":"16DBRUNIB","sname":"Université Alger 3","nbl":"4","stype":"bus","cid":"1623","cname":"Dely Ibrahim"},
{"scode":"16DEBAHBB","sname":"Aeroport d'Alger H.B","nbl":"6","stype":"bus","cid":"1620","cname":"Dar El Beïda"},
{"scode":"16DEBCN1B","sname":"Camp Nord - Dar el beida -","nbl":"2","stype":"bus","cid":"1620","cname":"Dar El Beïda"},
{"scode":"16DEBHMZB","sname":"El Hamiz","nbl":"14","stype":"bus","cid":"1620","cname":"Dar El Beïda"},
{"scode":"16DEBHZPB","sname":"El Hamiz - Commissariat de police -","nbl":"10","stype":"bus","cid":"1620","cname":"Dar El Beïda"},
{"scode":"16DEBMQ2B","sname":"Mosquée Ahmed Hammani","nbl":"1","stype":"bus","cid":"1620","cname":"Dar El Beïda"},
{"scode":"16DEBMRJB","sname":"El Merdja","nbl":"8","stype":"bus","cid":"1620","cname":"Dar El Beïda"},
{"scode":"16DEBMTOB","sname":"Meteo","nbl":"3","stype":"bus","cid":"1620","cname":"Dar El Beïda"},
{"scode":"16DEBSNTB","sname":"SNTP","nbl":"10","stype":"bus","cid":"1620","cname":"Dar El Beïda"},
{"scode":"16DEBTRMB","sname":"Dar el beida (Terminus)","nbl":"5","stype":"bus","cid":"1620","cname":"Dar El Beïda"},
{"scode":"16DJKAPCB","sname":"Mairie de Gue de Constantine","nbl":"2","stype":"bus","cid":"1626","cname":"Gue de Constantine"},
{"scode":"16DJKBIOB","sname":"Biotic","nbl":"12","stype":"bus","cid":"1626","cname":"Gue de Constantine"},
{"scode":"16DJKGUEB","sname":"Gue de Constantine","nbl":"10","stype":"bus","cid":"1626","cname":"Gue de Constantine"},
{"scode":"16DJKHMTB","sname":"Hôpital militaire","nbl":"6","stype":"bus","cid":"1626","cname":"Gue de Constantine"},
{"scode":"16DJKHYTB","sname":"Cité El-Hayat","nbl":"12","stype":"bus","cid":"1626","cname":"Gue de Constantine"},
{"scode":"16DJKKRMB","sname":"Oued El-Karma","nbl":"6","stype":"bus","cid":"1626","cname":"Gue de Constantine"},
{"scode":"16DJKMADB","sname":"ONAB","nbl":"8","stype":"bus","cid":"1626","cname":"Gue de Constantine"},
{"scode":"16DJKMLHB","sname":"Ain El-Malha","nbl":"4","stype":"bus","cid":"1626","cname":"Gue de Constantine"},
{"scode":"16DJKPNTB","sname":"Pont Semmar","nbl":"4","stype":"bus","cid":"1626","cname":"Gue de Constantine"},
{"scode":"16DJKSEMB","sname":"Semmar","nbl":"16","stype":"bus","cid":"1626","cname":"Gue de Constantine"},
{"scode":"16DJKSG7B","sname":"Sonelgaz (700 bureaux)","nbl":"6","stype":"bus","cid":"1626","cname":"Gue de Constantine"},
{"scode":"16DJKSTDB","sname":"Stade Semmar","nbl":"2","stype":"bus","cid":"1626","cname":"Gue de Constantine"},
{"scode":"16DJKTEAB","sname":"Cité Taher El-Ayeb","nbl":"6","stype":"bus","cid":"1626","cname":"Gue de Constantine"},
{"scode":"16DJKTF1B","sname":"Gare SNTF Gue de Constantine","nbl":"2","stype":"bus","cid":"1626","cname":"Gue de Constantine"},
{"scode":"16DJR4CHB","sname":"4 chemins","nbl":"8","stype":"bus","cid":"1616","cname":"Bachdjerrah"},
{"scode":"16DJRATLM","sname":"Halte des Ateliers","nbl":"2","stype":"metro","cid":"1616","cname":"Bachdjerrah"},
{"scode":"16DJRCREB","sname":"Cressonière","nbl":"1","stype":"bus","cid":"1616","cname":"Bachdjerrah"},
{"scode":"16DJRDDJB","sname":"Diar Djemaa","nbl":"3","stype":"bus","cid":"1616","cname":"Bachdjerrah"},
{"scode":"16DJRDJMB","sname":"Djenane Mabrouk","nbl":"2","stype":"bus","cid":"1616","cname":"Bachdjerrah"},
{"scode":"16DJRHAHB","sname":"Air Algérie \/ Metro","nbl":"8","stype":"bus","cid":"1616","cname":"Bachdjerrah"},
{"scode":"16DJRHCCB","sname":"Bachdjerrah Centre","nbl":"14","stype":"bus","cid":"1616","cname":"Bachdjerrah"},
{"scode":"16DJRHCCM","sname":"Bachdjerrah Centre","nbl":"2","stype":"metro","cid":"1616","cname":"Bachdjerrah"},
{"scode":"16DJRHTNB","sname":"Tennis","nbl":"6","stype":"bus","cid":"1616","cname":"Bachdjerrah"},
{"scode":"16DJRHTNM","sname":"Tennis","nbl":"2","stype":"metro","cid":"1616","cname":"Bachdjerrah"},
{"scode":"16DJRPTTB","sname":"Poste de Bachdjerrah","nbl":"1","stype":"bus","cid":"1616","cname":"Bachdjerrah"},
{"scode":"16DJRURGB","sname":"Cité Cherif Badi (Urgence)","nbl":"1","stype":"bus","cid":"1616","cname":"Bachdjerrah"},
{"scode":"16DNACTRB","sname":"Dergana Centre","nbl":"18","stype":"bus","cid":"1630","cname":"Bordj El Kiffan"},
{"scode":"16DNACTRT","sname":"Dergana Centre","nbl":"2","stype":"tramway","cid":"1630","cname":"Bordj El Kiffan"},
{"scode":"16DNACUBT","sname":"Dergana Cité","nbl":"2","stype":"tramway","cid":"1630","cname":"Bordj El Kiffan"},
{"scode":"16DNAMEDT","sname":"Faculté Biomédicale","nbl":"2","stype":"tramway","cid":"1630","cname":"Bordj El Kiffan"},
{"scode":"16DOUAGCB","sname":"Douera - Gare routiére -","nbl":"8","stype":"bus","cid":"1654","cname":"Douera"},
{"scode":"16DOUCNOB","sname":"Carrefour Douera Nord-Ouest","nbl":"2","stype":"bus","cid":"1654","cname":"Douera"},
{"scode":"16DOUCNPB","sname":"Cité CNEP Douera","nbl":"2","stype":"bus","cid":"1654","cname":"Douera"},
{"scode":"16DOUIN1B","sname":"Entrée Douera","nbl":"4","stype":"bus","cid":"1654","cname":"Douera"},
{"scode":"16DOUMDJB","sname":"Cité El Moudjahidine Douera","nbl":"2","stype":"bus","cid":"1654","cname":"Douera"},
{"scode":"16DOUOPGB","sname":"Cité OPGI Douera","nbl":"2","stype":"bus","cid":"1654","cname":"Douera"},
{"scode":"16DRC617B","sname":"Cité 617 logements","nbl":"2","stype":"bus","cid":"1653","cname":"Draria"},
{"scode":"16DRCFPAB","sname":"CFPA Draria","nbl":"2","stype":"bus","cid":"1653","cname":"Draria"},
{"scode":"16DRTEMMB","sname":"Cité Boudjemaa Temim","nbl":"2","stype":"bus","cid":"1653","cname":"Draria"},
{"scode":"16DRVENFB","sname":"Village d'enfants de Draria","nbl":"2","stype":"bus","cid":"1653","cname":"Draria"},
{"scode":"16DRVERTB","sname":"Bassin vert","nbl":"2","stype":"bus","cid":"1653","cname":"Draria"},
{"scode":"16ECS400B","sname":"Cité 400 logts Eucalyptus","nbl":"10","stype":"bus","cid":"1633","cname":"Les Eucalyptus"},
{"scode":"16ECS621B","sname":"Cité 621 Logts","nbl":"10","stype":"bus","cid":"1633","cname":"Les Eucalyptus"},
{"scode":"16ECS648B","sname":"Cité 648 Logts (Laâraibia)","nbl":"2","stype":"bus","cid":"1633","cname":"Les Eucalyptus"},
{"scode":"16ECS668B","sname":"Cité 668 Logts - FNPOS -","nbl":"4","stype":"bus","cid":"1633","cname":"Les Eucalyptus"},
{"scode":"16ECSADLB","sname":"Cité AADL Eucalyptus","nbl":"10","stype":"bus","cid":"1633","cname":"Les Eucalyptus"},
{"scode":"16ECSAGCB","sname":"Eucalyptus Station de bus","nbl":"6","stype":"bus","cid":"1633","cname":"Les Eucalyptus"},
{"scode":"16ECSAPCB","sname":"Siége APC Eucalyptus","nbl":"10","stype":"bus","cid":"1633","cname":"Les Eucalyptus"},
{"scode":"16ECSCAKB","sname":"Cité Emir Abd El-Kader","nbl":"6","stype":"bus","cid":"1633","cname":"Les Eucalyptus"},
{"scode":"16ECSDALB","sname":"Cité Ed-Dalia","nbl":"4","stype":"bus","cid":"1633","cname":"Les Eucalyptus"},
{"scode":"16ECSDJ1B","sname":"Cité El Djoumhouria","nbl":"2","stype":"bus","cid":"1633","cname":"Les Eucalyptus"},
{"scode":"16ECSDJ2B","sname":"El Djoumhouria","nbl":"2","stype":"bus","cid":"1633","cname":"Les Eucalyptus"},
{"scode":"16ECSDJ3B","sname":"Mosquée Aboudhar El Ghifari","nbl":"2","stype":"bus","cid":"1633","cname":"Les Eucalyptus"},
{"scode":"16ECSDJ4B","sname":"El Djoumhouria (Sortie Sud)","nbl":"2","stype":"bus","cid":"1633","cname":"Les Eucalyptus"},
{"scode":"16ECSEAKB","sname":"Ecole Emir Abd El-Kader","nbl":"4","stype":"bus","cid":"1633","cname":"Les Eucalyptus"},
{"scode":"16ECSGR1B","sname":"Marché de gros des Eucalyptus","nbl":"14","stype":"bus","cid":"1633","cname":"Les Eucalyptus"},
{"scode":"16ECSHAJB","sname":"Ouled el hadj","nbl":"2","stype":"bus","cid":"1633","cname":"Les Eucalyptus"},
{"scode":"16ECSISMB","sname":"Mosquée Prophéte Ismail - Ramdania -","nbl":"2","stype":"bus","cid":"1633","cname":"Les Eucalyptus"},
{"scode":"16ECSKF1B","sname":"Intersection Kourifa Eucalyptus","nbl":"4","stype":"bus","cid":"1633","cname":"Les Eucalyptus"},
{"scode":"16ECSKF2B","sname":"Cité Kourifa Eucalyptus","nbl":"2","stype":"bus","cid":"1633","cname":"Les Eucalyptus"},
{"scode":"16ECSLRMB","sname":"Lycée Ramdania","nbl":"4","stype":"bus","cid":"1633","cname":"Les Eucalyptus"},
{"scode":"16ECSMESB","sname":"Lycée Messaouda Djida","nbl":"2","stype":"bus","cid":"1633","cname":"Les Eucalyptus"},
{"scode":"16ECSMGFB","sname":"Ecole Salah MAUGAFI","nbl":"2","stype":"bus","cid":"1633","cname":"Les Eucalyptus"},
{"scode":"16ECSMHDB","sname":"Cimetiére Mahieddine - Moksib -","nbl":"2","stype":"bus","cid":"1633","cname":"Les Eucalyptus"},
{"scode":"16ECSMOSB","sname":"Mosquée Mousâab Ibn Oumaïr","nbl":"4","stype":"bus","cid":"1633","cname":"Les Eucalyptus"},
{"scode":"16ECSOUTB","sname":"Sortie Eucalyptus","nbl":"10","stype":"bus","cid":"1633","cname":"Les Eucalyptus"},
{"scode":"16ECSREDB","sname":"Salle omnisports - Château rouge -","nbl":"10","stype":"bus","cid":"1633","cname":"Les Eucalyptus"},
{"scode":"16ECSRMDB","sname":"Cité Ramdania","nbl":"2","stype":"bus","cid":"1633","cname":"Les Eucalyptus"},
{"scode":"16ECSSLIB","sname":"Nouvelle Cité Slimani","nbl":"9","stype":"bus","cid":"1633","cname":"Les Eucalyptus"},
{"scode":"16ECSTICB","sname":"INPTIC","nbl":"10","stype":"bus","cid":"1633","cname":"Les Eucalyptus"},
{"scode":"16ECSZAOB","sname":"Cité Zouaoui - Eucalyptus -","nbl":"2","stype":"bus","cid":"1633","cname":"Les Eucalyptus"},
{"scode":"16HERLRBB","sname":"Ouled Larbi","nbl":"2","stype":"bus","cid":"1641","cname":"Heraoua"},
{"scode":"16HERMRAB","sname":"Maamria","nbl":"2","stype":"bus","cid":"1641","cname":"Heraoua"},
{"scode":"16HMDHORB","sname":"Horizons bleus","nbl":"4","stype":"bus","cid":"1625","cname":"Raïs Hamidou"},
{"scode":"16HMDPTEB","sname":"Raïs Hamidou 2","nbl":"8","stype":"bus","cid":"1625","cname":"Raïs Hamidou"},
{"scode":"16HMDRH1B","sname":"Raïs Hamidou 1","nbl":"4","stype":"bus","cid":"1625","cname":"Raïs Hamidou"},
{"scode":"16HMDVIGB","sname":"La Vigie","nbl":"4","stype":"bus","cid":"1625","cname":"Raïs Hamidou"},
{"scode":"16HMTCTRB","sname":"Baïnem","nbl":"8","stype":"bus","cid":"1624","cname":"El Hammamet"},
{"scode":"16HRCBEKT","sname":"Bekri Bouguera","nbl":"2","stype":"tramway","cid":"1613","cname":"El Harrach"},
{"scode":"16HRCBFRB","sname":"Belfort","nbl":"2","stype":"bus","cid":"1613","cname":"El Harrach"},
{"scode":"16HRCBMTB","sname":"Boumaati","nbl":"16","stype":"bus","cid":"1613","cname":"El Harrach"},
{"scode":"16HRCCMBB","sname":"Centre Mokhtar Belkacem","nbl":"2","stype":"bus","cid":"1613","cname":"El Harrach"},
{"scode":"16HRCECOB","sname":"ECOTEH","nbl":"2","stype":"bus","cid":"1613","cname":"El Harrach"},
{"scode":"16HRCGARB","sname":"Gare SNTF El Harrach","nbl":"10","stype":"bus","cid":"1613","cname":"El Harrach"},
{"scode":"16HRCGARM","sname":"El Harrache Gare","nbl":"2","stype":"metro","cid":"1613","cname":"El Harrach"},
{"scode":"16HRCHCCB","sname":"El Harrache (Centre)","nbl":"34","stype":"bus","cid":"1613","cname":"El Harrach"},
{"scode":"16HRCHCCM","sname":"El Harrache (Centre)","nbl":"2","stype":"metro","cid":"1613","cname":"El Harrach"},
{"scode":"16HRCKF1B","sname":"Cité Kourifa 1","nbl":"10","stype":"bus","cid":"1613","cname":"El Harrach"},
{"scode":"16HRCKF2B","sname":"Cité Kourifa 2","nbl":"10","stype":"bus","cid":"1613","cname":"El Harrach"},
{"scode":"16HRCMBRB","sname":"Sidi Mbarek El-Harrach","nbl":"10","stype":"bus","cid":"1613","cname":"El Harrach"},
{"scode":"16HRCNAFB","sname":"Unité Naftal","nbl":"10","stype":"bus","cid":"1613","cname":"El Harrach"},
{"scode":"16HRCPONT","sname":"Pont El Harrach","nbl":"2","stype":"tramway","cid":"1613","cname":"El Harrach"},
{"scode":"16HRCRADB","sname":"La Radieuse","nbl":"21","stype":"bus","cid":"1613","cname":"El Harrach"},
{"scode":"16HRCVUET","sname":"Belle Vue","nbl":"2","stype":"tramway","cid":"1613","cname":"El Harrach"},
{"scode":"16HRCZMRB","sname":"Hôpital Zemirli","nbl":"4","stype":"bus","cid":"1613","cname":"El Harrach"},
{"scode":"16HSDAMIB","sname":"Cité Amirouche","nbl":"3","stype":"bus","cid":"1617","cname":"Hussein Dey"},
{"scode":"16HSDAMIM","sname":"Cité Amirouche","nbl":"2","stype":"metro","cid":"1617","cname":"Hussein Dey"},
{"scode":"16HSDAN1B","sname":"El-Anasser - Station multimodale -","nbl":"3","stype":"bus","cid":"1617","cname":"Hussein Dey"},
{"scode":"16HSDANSB","sname":"Ruisseau \/ El-anassers","nbl":"2","stype":"bus","cid":"1617","cname":"Hussein Dey"},
{"scode":"16HSDANSL","sname":"Téléphérique El Anassers","nbl":"2","stype":"Téléphérique","cid":"1617","cname":"Hussein Dey"},
{"scode":"16HSDANSM","sname":"Ruisseau (Les fusillés)","nbl":"2","stype":"metro","cid":"1617","cname":"Hussein Dey"},
{"scode":"16HSDANST","sname":"Ruisseau العناصر","nbl":"2","stype":"tramway","cid":"1617","cname":"Hussein Dey"},
{"scode":"16HSDCR2B","sname":"Caroubier - Gare SNTF -","nbl":"1","stype":"bus","cid":"1617","cname":"Hussein Dey"},
{"scode":"16HSDCRBB","sname":"Caroubier - Centre equestre\/Fac -","nbl":"20","stype":"bus","cid":"1617","cname":"Hussein Dey"},
{"scode":"16HSDCRBT","sname":"Carroubier","nbl":"2","stype":"tramway","cid":"1617","cname":"Hussein Dey"},
{"scode":"16HSDCTRB","sname":"Hussein Dey - Avenue ALN -","nbl":"10","stype":"bus","cid":"1617","cname":"Hussein Dey"},
{"scode":"16HSDFG1B","sname":"Pont des fusillés - Avenue ALN -","nbl":"5","stype":"bus","cid":"1617","cname":"Hussein Dey"},
{"scode":"16HSDFG2B","sname":"Bd Mohamed MERBOUCHE","nbl":"6","stype":"bus","cid":"1617","cname":"Hussein Dey"},
{"scode":"16HSDFUST","sname":"Les Fusillés","nbl":"2","stype":"tramway","cid":"1617","cname":"Hussein Dey"},
{"scode":"16HSDGLCB","sname":"Bel Air - La Glacière","nbl":"21","stype":"bus","cid":"1617","cname":"Hussein Dey"},
{"scode":"16HSDGLCT","sname":"La Glacière","nbl":"2","stype":"tramway","cid":"1617","cname":"Hussein Dey"},
{"scode":"16HSDGRTB","sname":"Caroubier - Gare routiére -","nbl":"24","stype":"bus","cid":"1617","cname":"Hussein Dey"},
{"scode":"16HSDHAMT","sname":"Tripoli - Hamadèche","nbl":"2","stype":"tramway","cid":"1617","cname":"Hussein Dey"},
{"scode":"16HSDHPNB","sname":"Hôpital Parnet","nbl":"3","stype":"bus","cid":"1617","cname":"Hussein Dey"},
{"scode":"16HSDKNSB","sname":"Ouedkniss","nbl":"5","stype":"bus","cid":"1617","cname":"Hussein Dey"},
{"scode":"16HSDMAGT","sname":"Tripoli - Magharia","nbl":"2","stype":"tramway","cid":"1617","cname":"Hussein Dey"},
{"scode":"16HSDMESB","sname":"Cité Mer et Soleil","nbl":"3","stype":"bus","cid":"1617","cname":"Hussein Dey"},
{"scode":"16HSDMESM","sname":"Cité Mer et Soleil","nbl":"2","stype":"metro","cid":"1617","cname":"Hussein Dey"},
{"scode":"16HSDMOST","sname":"Tripoli - Mosquée","nbl":"2","stype":"tramway","cid":"1617","cname":"Hussein Dey"},
{"scode":"16HSDRESB","sname":"Résidence","nbl":"3","stype":"bus","cid":"1617","cname":"Hussein Dey"},
{"scode":"16HSDTLBT","sname":"Tripoli -Thaalibia","nbl":"2","stype":"tramway","cid":"1617","cname":"Hussein Dey"},
{"scode":"16HSDTXIB","sname":"Caroubier - Station de Taxis -","nbl":"2","stype":"bus","cid":"1617","cname":"Hussein Dey"},
{"scode":"16HSDZPTB","sname":"Emiliano Zapata \/ Palais de justice","nbl":"10","stype":"bus","cid":"1617","cname":"Hussein Dey"},
{"scode":"16HYDQDSB","sname":"Place El-Quods","nbl":"4","stype":"bus","cid":"1628","cname":"Hydra"},
{"scode":"16HYDSMAB","sname":"Place Al Smaa","nbl":"4","stype":"bus","cid":"1628","cname":"Hydra"},
{"scode":"16JRHTN2B","sname":"Bachdjerrah Tennis 2","nbl":"1","stype":"bus","cid":"1616","cname":"Bachdjerrah"},
{"scode":"16KBAAFAB","sname":"El-Afia","nbl":"2","stype":"bus","cid":"1618","cname":"Kouba"},
{"scode":"16KBAANSB","sname":"Cité Les Anassers \/ MAE","nbl":"2","stype":"bus","cid":"1618","cname":"Kouba"},
{"scode":"16KBAAP1B","sname":"Appreval (vers Ben Omar)","nbl":"8","stype":"bus","cid":"1618","cname":"Kouba"},
{"scode":"16KBAAP2B","sname":"Appreval (vers Semmar)","nbl":"2","stype":"bus","cid":"1618","cname":"Kouba"},
{"scode":"16KBAAPCB","sname":"Siége APC Kouba","nbl":"2","stype":"bus","cid":"1618","cname":"Kouba"},
{"scode":"16KBABAHB","sname":"Cité El Bahia","nbl":"6","stype":"bus","cid":"1618","cname":"Kouba"},
{"scode":"16KBABDRB","sname":"Station Hai el Badr","nbl":"9","stype":"bus","cid":"1618","cname":"Kouba"},
{"scode":"16KBABDRM","sname":"Hai el badr","nbl":"4","stype":"metro","cid":"1618","cname":"Kouba"},
{"scode":"16KBACALB","sname":"Calvaire","nbl":"2","stype":"bus","cid":"1618","cname":"Kouba"},
{"scode":"16KBACOPB","sname":"Cité COPEMADE","nbl":"2","stype":"bus","cid":"1618","cname":"Kouba"},
{"scode":"16KBACRXB","sname":"La Croix","nbl":"4","stype":"bus","cid":"1618","cname":"Kouba"},
{"scode":"16KBACTRB","sname":"Ben Omar","nbl":"20","stype":"bus","cid":"1618","cname":"Kouba"},
{"scode":"16KBAGD1B","sname":"Garidi 1","nbl":"8","stype":"bus","cid":"1618","cname":"Kouba"},
{"scode":"16KBAGD2B","sname":"Garidi 2","nbl":"6","stype":"bus","cid":"1618","cname":"Kouba"},
{"scode":"16KBAGDPB","sname":"Garidi - Pont","nbl":"1","stype":"bus","cid":"1618","cname":"Kouba"},
{"scode":"16KBAHDHB","sname":"Hôpital Drid Hocine","nbl":"3","stype":"bus","cid":"1618","cname":"Kouba"},
{"scode":"16KBAMCLB","sname":"Lotissement Michel","nbl":"3","stype":"bus","cid":"1618","cname":"Kouba"},
{"scode":"16KBAOASB","sname":"Oasis","nbl":"2","stype":"bus","cid":"1618","cname":"Kouba"},
{"scode":"16KBAOBHB","sname":"Stade Omar Benhaddad","nbl":"6","stype":"bus","cid":"1618","cname":"Kouba"},
{"scode":"16KBAOK2B","sname":"Ouedkniss 2","nbl":"2","stype":"bus","cid":"1618","cname":"Kouba"},
{"scode":"16KBASLMB","sname":"Fréres Abdeselami","nbl":"4","stype":"bus","cid":"1618","cname":"Kouba"},
{"scode":"16KBAVKBB","sname":"Vieux Kouba","nbl":"4","stype":"bus","cid":"1618","cname":"Kouba"},
{"scode":"16KBAVUEB","sname":"Jolie vue","nbl":"6","stype":"bus","cid":"1618","cname":"Kouba"},
{"scode":"16KHRCHSB","sname":"Cherifi Said - Mosquée Ali Chentir -","nbl":"2","stype":"bus","cid":"1656","cname":"Khraicia"},
{"scode":"16KHRLRSB","sname":"Cité Laroussi Hamoud - Haouch Gazouz -","nbl":"2","stype":"bus","cid":"1656","cname":"Khraicia"},
{"scode":"16KORFRAB","sname":"Climat de France","nbl":"4","stype":"bus","cid":"1608","cname":"Oued Koriche"},
{"scode":"16KORPC1B","sname":"Frais Vallon - Protection","nbl":"2","stype":"bus","cid":"1608","cname":"Oued Koriche"},
{"scode":"16KORSCOB","sname":"Scotto Nadal","nbl":"4","stype":"bus","cid":"1608","cname":"Oued Koriche"},
{"scode":"16KORTRIB","sname":"Triolet","nbl":"4","stype":"bus","cid":"1608","cname":"Oued Koriche"},
{"scode":"16MADCLTB","sname":"Palais de la culture","nbl":"1","stype":"bus","cid":"1603","cname":"El Madania"},
{"scode":"16MADCLTL","sname":"Palais de la culture","nbl":"2","stype":"Téléphérique","cid":"1603","cname":"El Madania"},
{"scode":"16MADMQ1B","sname":"Maquam E'Chahid","nbl":"4","stype":"bus","cid":"1603","cname":"El Madania"},
{"scode":"16MADMQ1L","sname":"Maquam Echahid","nbl":"2","stype":"Téléphérique","cid":"1603","cname":"El Madania"},
{"scode":"16MDAPANB","sname":"Panorama","nbl":"3","stype":"bus","cid":"1603","cname":"El Madania"},
{"scode":"16MDATUNB","sname":"Tunnel","nbl":"4","stype":"bus","cid":"1603","cname":"El Madania"},
{"scode":"16MDCTR1B","sname":"El-Madania","nbl":"4","stype":"bus","cid":"1603","cname":"El Madania"},
{"scode":"16MDFMD1B","sname":"Fréres Madani","nbl":"4","stype":"bus","cid":"1603","cname":"El Madania"},
{"scode":"16MDMHCLB","sname":"Diar Mahcoul","nbl":"4","stype":"bus","cid":"1603","cname":"El Madania"},
{"scode":"16MDMHCLL","sname":"Diar el Mahçoul","nbl":"2","stype":"Téléphérique","cid":"1603","cname":"El Madania"},
{"scode":"16MGMAYAB","sname":"Cité Maya","nbl":"3","stype":"bus","cid":"1631","cname":"El Magharia"},
{"scode":"16MH1MAIB","sname":"Place 1er Mai","nbl":"27","stype":"bus","cid":"1602","cname":"Sidi M`Hamed"},
{"scode":"16MH1MAIM","sname":"Place 1er Mai","nbl":"2","stype":"metro","cid":"1602","cname":"Sidi M`Hamed"},
{"scode":"16MHHMLNB","sname":"Moulin","nbl":"6","stype":"bus","cid":"1602","cname":"Sidi M`Hamed"},
{"scode":"16MHHSAFB","sname":"Hotel Es-Safir","nbl":"18","stype":"bus","cid":"1602","cname":"Sidi M`Hamed"},
{"scode":"16MHMAURB","sname":"Mauretania","nbl":"6","stype":"bus","cid":"1602","cname":"Sidi M`Hamed"},
{"scode":"16MHPPL1B","sname":"Palais du peuple","nbl":"5","stype":"bus","cid":"1602","cname":"Sidi M`Hamed"},
{"scode":"16MLHADLB","sname":"AADL Ain Malha","nbl":"2","stype":"bus","cid":"1626","cname":"Gue de Constantine"},
{"scode":"16MLHCHZB","sname":"CEM El Hachemi Zeddam","nbl":"2","stype":"bus","cid":"1626","cname":"Gue de Constantine"},
{"scode":"16MLHCZMB","sname":"CEM Zouaoui Mohamed","nbl":"2","stype":"bus","cid":"1626","cname":"Gue de Constantine"},
{"scode":"16MLHEC1B","sname":"Ecole Ain Malha Djadida","nbl":"2","stype":"bus","cid":"1626","cname":"Gue de Constantine"},
{"scode":"16MLHMIKB","sname":"Mosquée El-Ikhlas","nbl":"2","stype":"bus","cid":"1626","cname":"Gue de Constantine"},
{"scode":"16MLHMSDB","sname":"Mosquée Aboubakr Es-seddik","nbl":"1","stype":"bus","cid":"1626","cname":"Gue de Constantine"},
{"scode":"16MLHRN1B","sname":"Intersection Ain Malha RN1","nbl":"2","stype":"bus","cid":"1626","cname":"Gue de Constantine"},
{"scode":"16MLM11DB","sname":"Place 11 Décembre 1960 - Mahelma -","nbl":"10","stype":"bus","cid":"1647","cname":"Mahelma"},
{"scode":"16MLMBNRB","sname":"Sidi Bennour","nbl":"2","stype":"bus","cid":"1647","cname":"Mahelma"},
{"scode":"16MLMCSBB","sname":"Cimetiére Sidi Bennour (AADL)","nbl":"2","stype":"bus","cid":"1647","cname":"Mahelma"},
{"scode":"16MLMCTRB","sname":"Mahelma - Centre","nbl":"10","stype":"bus","cid":"1647","cname":"Mahelma"},
{"scode":"16MLMCU1B","sname":"Cité Universitaire Sidi Abdellah","nbl":"10","stype":"bus","cid":"1647","cname":"Mahelma"},
{"scode":"16MLMDMLB","sname":"Douar Mouloud (Carrefour)","nbl":"2","stype":"bus","cid":"1647","cname":"Mahelma"},
{"scode":"16MLMEBBB","sname":"Ecole Abd El-Hamid Ben Badis","nbl":"1","stype":"bus","cid":"1647","cname":"Mahelma"},
{"scode":"16MLMOKBB","sname":"Mosquée Okba Ibn Nafaa Mahelma","nbl":"8","stype":"bus","cid":"1647","cname":"Mahelma"},
{"scode":"16MLMSNCB","sname":"Senechar","nbl":"2","stype":"bus","cid":"1647","cname":"Mahelma"},
{"scode":"16MLMTF1B","sname":"Gare SNTF Université Mahelma","nbl":"6","stype":"bus","cid":"1647","cname":"Mahelma"},
{"scode":"16MLMZCLB","sname":"Zaatria (Polyclinique)","nbl":"2","stype":"bus","cid":"1647","cname":"Mahelma"},
{"scode":"16MLMZDLB","sname":"AADL Zaatria","nbl":"2","stype":"bus","cid":"1647","cname":"Mahelma"},
{"scode":"16MOH001B","sname":"Mohamadia","nbl":"20","stype":"bus","cid":"1629","cname":"Mohammadia"},
{"scode":"16MOH5M1B","sname":"Cinq Maisons (RN5)","nbl":"20","stype":"bus","cid":"1629","cname":"Mohammadia"},
{"scode":"16MOH5M2T","sname":"Cinq Maisons","nbl":"2","stype":"tramway","cid":"1629","cname":"Mohammadia"},
{"scode":"16MOHBNNB","sname":"Cité Mokhtar Zerhouni","nbl":"2","stype":"bus","cid":"1629","cname":"Mohammadia"},
{"scode":"16MOHBNNT","sname":"Cité Mokhtar Zerhouni","nbl":"2","stype":"tramway","cid":"1629","cname":"Mohammadia"},
{"scode":"16MOHPINT","sname":"Les Pins","nbl":"2","stype":"tramway","cid":"1629","cname":"Mohammadia"},
{"scode":"16MOHSFXT","sname":"Foire d'Alger","nbl":"2","stype":"tramway","cid":"1629","cname":"Mohammadia"},
{"scode":"16MOHSNDB","sname":"Sonda","nbl":"6","stype":"bus","cid":"1629","cname":"Mohammadia"},
{"scode":"16MOHSTXB","sname":"FITAL","nbl":"19","stype":"bus","cid":"1629","cname":"Mohammadia"},
{"scode":"16MOHTAMT","sname":"Tamaris","nbl":"2","stype":"tramway","cid":"1629","cname":"Mohammadia"},
{"scode":"16MORBMMB","sname":"Lycée Bouamama","nbl":"1","stype":"bus","cid":"1627","cname":"El Mouradia"},
{"scode":"16MORCTRB","sname":"El-Mouradia","nbl":"1","stype":"bus","cid":"1627","cname":"El Mouradia"},
{"scode":"16MORCVLB","sname":"Colonne Voirole","nbl":"4","stype":"bus","cid":"1627","cname":"El Mouradia"},
{"scode":"16MORHDZB","sname":"Hôtel El-Djazair","nbl":"5","stype":"bus","cid":"1627","cname":"El Mouradia"},
{"scode":"16MORSDNB","sname":"Carrefour Souidani","nbl":"5","stype":"bus","cid":"1627","cname":"El Mouradia"},
{"scode":"16MRGMKTB","sname":"Tessala El merdja - Marché -","nbl":"2","stype":"bus","cid":"1635","cname":"Tessala El Merdja"},
{"scode":"16MRGTF1B","sname":"Gare SNTF Tessala El merdja","nbl":"2","stype":"bus","cid":"1635","cname":"Tessala El Merdja"},
{"scode":"16MRJCTRB","sname":"Tessala El merdja","nbl":"2","stype":"bus","cid":"1635","cname":"Tessala El Merdja"},
{"scode":"16NDJ006B","sname":"Fleuriste","nbl":"8","stype":"bus","cid":"1626","cname":"Gue de Constantine"},
{"scode":"16NDJ721B","sname":"720 lgmts 1","nbl":"2","stype":"bus","cid":"1626","cname":"Gue de Constantine"},
{"scode":"16NDJ721M","sname":"Ain Naadja 1","nbl":"2","stype":"metro","cid":"1626","cname":"Gue de Constantine"},
{"scode":"16NDJ722B","sname":"720 lgmts 2","nbl":"2","stype":"bus","cid":"1626","cname":"Gue de Constantine"},
{"scode":"16NDJ722M","sname":"Ain Naadja 2","nbl":"2","stype":"metro","cid":"1626","cname":"Gue de Constantine"},
{"scode":"16NDJ723B","sname":"Cité 720 logements 1","nbl":"6","stype":"bus","cid":"1626","cname":"Gue de Constantine"},
{"scode":"16NDJ724B","sname":"Cité 720 logements 2","nbl":"6","stype":"bus","cid":"1626","cname":"Gue de Constantine"},
{"scode":"16NDJAGCB","sname":"Ain Naadja (Station de bus)","nbl":"12","stype":"bus","cid":"1626","cname":"Gue de Constantine"},
{"scode":"16NDJCHTB","sname":"Château d'eau","nbl":"1","stype":"bus","cid":"1626","cname":"Gue de Constantine"},
{"scode":"16NDJGR1B","sname":"Ain Naadja (Gare SNTF)","nbl":"8","stype":"bus","cid":"1626","cname":"Gue de Constantine"},
{"scode":"16NDJKRSB","sname":"El-kares \/ AADL","nbl":"6","stype":"bus","cid":"1626","cname":"Gue de Constantine"},
{"scode":"16NDJMK1B","sname":"Marché de Ain Naadja","nbl":"8","stype":"bus","cid":"1626","cname":"Gue de Constantine"},
{"scode":"16NDJMKTB","sname":"Marché couvert 720","nbl":"2","stype":"bus","cid":"1626","cname":"Gue de Constantine"},
{"scode":"16NDJOKBB","sname":"Mosquée Okba Ibn Nafaa","nbl":"11","stype":"bus","cid":"1626","cname":"Gue de Constantine"},
{"scode":"16NDJSFSB","sname":"Safsafa","nbl":"6","stype":"bus","cid":"1626","cname":"Gue de Constantine"},
{"scode":"16OCCCHBB","sname":"Cité Chaibia","nbl":"2","stype":"bus","cid":"1636","cname":"Ouled Chebel"},
{"scode":"16OFCFPAB","sname":"CFPA Ouled Fayet","nbl":"2","stype":"bus","cid":"1651","cname":"Ouled Fayet"},
{"scode":"16OFHBF1B","sname":"Hôtel Le Beau Fayet","nbl":"4","stype":"bus","cid":"1651","cname":"Ouled Fayet"},
{"scode":"16OFMSQ1B","sname":"Mosquée Er-rahma - Ouled Fayet -","nbl":"2","stype":"bus","cid":"1651","cname":"Ouled Fayet"},
{"scode":"16OFRUB3B","sname":"Résidence Universitaire 3 Ouled Fayet","nbl":"2","stype":"bus","cid":"1651","cname":"Ouled Fayet"},
{"scode":"16OFTCICB","sname":"CIC3","nbl":"4","stype":"bus","cid":"1651","cname":"Ouled Fayet"},
{"scode":"16OFTCTRB","sname":"Mairie de Ouled Fayet","nbl":"2","stype":"bus","cid":"1651","cname":"Ouled Fayet"},
{"scode":"16OFTOOAB","sname":"Oued \/ Ooredoo","nbl":"2","stype":"bus","cid":"1651","cname":"Ouled Fayet"},
{"scode":"16OS0001B","sname":"ENSV","nbl":"6","stype":"bus","cid":"1615","cname":"Oued Smar"},
{"scode":"16OSALIAB","sname":"El-Alia (RN5)","nbl":"24","stype":"bus","cid":"1615","cname":"Oued Smar"},
{"scode":"16OSBEAUB","sname":"Beau lieu","nbl":"6","stype":"bus","cid":"1615","cname":"Oued Smar"},
{"scode":"16OSITEMB","sname":"ITEEM","nbl":"6","stype":"bus","cid":"1615","cname":"Oued Smar"},
{"scode":"16OSLYCEB","sname":"Lycée El Bayrouni","nbl":"6","stype":"bus","cid":"1615","cname":"Oued Smar"},
{"scode":"16OSMSQ1B","sname":"Mosquée Hassan Ben Thabet","nbl":"4","stype":"bus","cid":"1615","cname":"Oued Smar"},
{"scode":"16OSRNPTB","sname":"Oued Smar (Rondpoint)","nbl":"6","stype":"bus","cid":"1615","cname":"Oued Smar"},
{"scode":"16OSZI01B","sname":"Z.I. de Oued Smar","nbl":"4","stype":"bus","cid":"1615","cname":"Oued Smar"},
{"scode":"16RAH802B","sname":"Rahmania (8 Février)","nbl":"4","stype":"bus","cid":"1648","cname":"Rahmania"},
{"scode":"16RAHADLB","sname":"AADL Rahmania","nbl":"2","stype":"bus","cid":"1648","cname":"Rahmania"},
{"scode":"16RAHCTRB","sname":"Rahmania","nbl":"4","stype":"bus","cid":"1648","cname":"Rahmania"},
{"scode":"16RAHNMNB","sname":"Cité Naamane Benamri (Rahmania)","nbl":"2","stype":"bus","cid":"1648","cname":"Rahmania"},
{"scode":"16RBA154B","sname":"Cité 1540 logts","nbl":"6","stype":"bus","cid":"1642","cname":"Rouïba"},
{"scode":"16RBABC2B","sname":"Ouled Laïd - Ben Choubane -","nbl":"2","stype":"bus","cid":"1642","cname":"Rouïba"},
{"scode":"16RBABCHB","sname":"Ben Choubane","nbl":"4","stype":"bus","cid":"1642","cname":"Rouïba"},
{"scode":"16RBACBAB","sname":"Cité Boualem El-Aloui","nbl":"4","stype":"bus","cid":"1642","cname":"Rouïba"},
{"scode":"16RBACHBB","sname":"Cité Chabou","nbl":"4","stype":"bus","cid":"1642","cname":"Rouïba"},
{"scode":"16RBACNSB","sname":"El-Hamiz - Cité En-Nasr","nbl":"9","stype":"bus","cid":"1642","cname":"Rouïba"},
{"scode":"16RBACTRB","sname":"Rouiba (Centre)","nbl":"24","stype":"bus","cid":"1642","cname":"Rouïba"},
{"scode":"16RBADCMB","sname":"Domaine Chouaïb Mohamed","nbl":"1","stype":"bus","cid":"1642","cname":"Rouïba"},
{"scode":"16RBADGHB","sname":"Deghafla","nbl":"2","stype":"bus","cid":"1642","cname":"Rouïba"},
{"scode":"16RBADSBB","sname":"Domaine Si Boualem","nbl":"4","stype":"bus","cid":"1642","cname":"Rouïba"},
{"scode":"16RBAEMSB","sname":"MOBISCO Rouiba","nbl":"4","stype":"bus","cid":"1642","cname":"Rouïba"},
{"scode":"16RBAGDHB","sname":"Cimetiére Guedhia","nbl":"2","stype":"bus","cid":"1642","cname":"Rouïba"},
{"scode":"16RBAGZIB","sname":"Gare SNTF ZI Rouiba","nbl":"4","stype":"bus","cid":"1642","cname":"Rouïba"},
{"scode":"16RBAHC1B","sname":"Haouch Rouiba 1","nbl":"2","stype":"bus","cid":"1642","cname":"Rouïba"},
{"scode":"16RBAHC2B","sname":"Haouch Rouiba 2","nbl":"2","stype":"bus","cid":"1642","cname":"Rouïba"},
{"scode":"16RBAHSPB","sname":"Rouiba - Hopital","nbl":"3","stype":"bus","cid":"1642","cname":"Rouïba"},
{"scode":"16RBAIMCB","sname":"IMC Rouiba","nbl":"4","stype":"bus","cid":"1642","cname":"Rouïba"},
{"scode":"16RBAINFB","sname":"INFORBA","nbl":"6","stype":"bus","cid":"1642","cname":"Rouïba"},
{"scode":"16RBAISFB","sname":"ISFF","nbl":"4","stype":"bus","cid":"1642","cname":"Rouïba"},
{"scode":"16RBAMJ1B","sname":"Cité El Merdja (Commissariat)","nbl":"2","stype":"bus","cid":"1642","cname":"Rouïba"},
{"scode":"16RBAMRJB","sname":"Cité El Merdja","nbl":"2","stype":"bus","cid":"1642","cname":"Rouïba"},
{"scode":"16RBAMTSB","sname":"Mouatsa","nbl":"2","stype":"bus","cid":"1642","cname":"Rouïba"},
{"scode":"16RBARMLB","sname":"Haouch Rmel","nbl":"2","stype":"bus","cid":"1642","cname":"Rouïba"},
{"scode":"16RBASBTB","sname":"Sbaat","nbl":"2","stype":"bus","cid":"1642","cname":"Rouïba"},
{"scode":"16RBASCTB","sname":"Souachette","nbl":"8","stype":"bus","cid":"1642","cname":"Rouïba"},
{"scode":"16REGBRDB","sname":"Braidia","nbl":"2","stype":"bus","cid":"1643","cname":"Reghaïa"},
{"scode":"16REGCDMB","sname":"Cimetiere Des Martyrs","nbl":"2","stype":"bus","cid":"1643","cname":"Reghaïa"},
{"scode":"16REGCTRB","sname":"Reghaïa (Station de bus)","nbl":"10","stype":"bus","cid":"1643","cname":"Reghaïa"},
{"scode":"16REGDNCB","sname":"Cite Dnc Reghaia","nbl":"2","stype":"bus","cid":"1643","cname":"Reghaïa"},
{"scode":"16REGFCIB","sname":"Cite Faouci","nbl":"2","stype":"bus","cid":"1643","cname":"Reghaïa"},
{"scode":"16REGGTPB","sname":"GTP Reghaia","nbl":"4","stype":"bus","cid":"1643","cname":"Reghaïa"},
{"scode":"16REGHENB","sname":"Henkel Reghaia","nbl":"4","stype":"bus","cid":"1643","cname":"Reghaïa"},
{"scode":"16REGIRSB","sname":"Cité les Iris","nbl":"2","stype":"bus","cid":"1643","cname":"Reghaïa"},
{"scode":"16REGKERB","sname":"El Kerrouche","nbl":"2","stype":"bus","cid":"1643","cname":"Reghaïa"},
{"scode":"16REGMARB","sname":"Place Des Martyrs Reghaia","nbl":"2","stype":"bus","cid":"1643","cname":"Reghaïa"},
{"scode":"16REGMKTB","sname":"Marche","nbl":"4","stype":"bus","cid":"1643","cname":"Reghaïa"},
{"scode":"16REGNJHB","sname":"Cité AADL Reghaïa","nbl":"2","stype":"bus","cid":"1643","cname":"Reghaïa"},
{"scode":"16REGSELB","sname":"Seaal Heuraoua","nbl":"2","stype":"bus","cid":"1643","cname":"Reghaïa"},
{"scode":"16REGZYDB","sname":"Mosquée Tarik Ibn Ziyad (Les Iris)","nbl":"4","stype":"bus","cid":"1643","cname":"Reghaïa"},
{"scode":"16SAA11DB","sname":"Cité 11 Décembre Sidi Abdellah","nbl":"10","stype":"bus","cid":"1647","cname":"Mahelma"},
{"scode":"16SAAADLB","sname":"Cité AADL - Sidi Abdellah -","nbl":"8","stype":"bus","cid":"1647","cname":"Mahelma"},
{"scode":"16SAACTRB","sname":"Sidi Abdellah (Centre)","nbl":"8","stype":"bus","cid":"1647","cname":"Mahelma"},
{"scode":"16SDNAGCB","sname":"Souidania","nbl":"2","stype":"bus","cid":"1649","cname":"Souidania"},
{"scode":"16SDNCBLB","sname":"La côte blanche","nbl":"2","stype":"bus","cid":"1649","cname":"Souidania"},
{"scode":"16SDNCSBB","sname":"Cité Souidani BOUDJEMAA","nbl":"2","stype":"bus","cid":"1649","cname":"Souidania"},
{"scode":"16SHAADLB","sname":"Said Hamdine (AADL)","nbl":"16","stype":"bus","cid":"1609","cname":"Bir Mourad Raïs"},
{"scode":"16SLA648B","sname":"Cité 648 Logements Saoula","nbl":"2","stype":"bus","cid":"1657","cname":"Saoula"},
{"scode":"16SLABAAB","sname":"Baba Ali - Autoroute -","nbl":"12","stype":"bus","cid":"1657","cname":"Saoula"},
{"scode":"16SLARBOB","sname":"Résidence Belhadj Othman","nbl":"2","stype":"bus","cid":"1657","cname":"Saoula"},
{"scode":"16SMHBDOB","sname":"Musée National du Bardo","nbl":"2","stype":"bus","cid":"1602","cname":"Sidi M`Hamed"},
{"scode":"16SMHGR1B","sname":"Ghermoul 1 (Polyclinique)","nbl":"3","stype":"bus","cid":"1602","cname":"Sidi M`Hamed"},
{"scode":"16SMHGR2B","sname":"Ghermoul 2","nbl":"3","stype":"bus","cid":"1602","cname":"Sidi M`Hamed"},
{"scode":"16SMHHRCB","sname":"Harcha","nbl":"3","stype":"bus","cid":"1602","cname":"Sidi M`Hamed"},
{"scode":"16SMHMARB","sname":"Place Bd des Martyrs","nbl":"2","stype":"bus","cid":"1602","cname":"Sidi M`Hamed"},
{"scode":"16SMHMEDB","sname":"Fac de médecine (ex-Laperrine)","nbl":"3","stype":"bus","cid":"1602","cname":"Sidi M`Hamed"},
{"scode":"16SMHTV1B","sname":"E N T V","nbl":"2","stype":"bus","cid":"1602","cname":"Sidi M`Hamed"},
{"scode":"16SMSAGCB","sname":"Sidi Moussa (Station de bus)","nbl":"6","stype":"bus","cid":"1637","cname":"Sidi Moussa"},
{"scode":"16SMSBLDB","sname":"Domaine Si Belaid","nbl":"8","stype":"bus","cid":"1637","cname":"Sidi Moussa"},
{"scode":"16SMSBNJB","sname":"Haouch Benidja","nbl":"2","stype":"bus","cid":"1637","cname":"Sidi Moussa"},
{"scode":"16SMSCLIB","sname":"Polyclinique de Sidi Moussa","nbl":"6","stype":"bus","cid":"1637","cname":"Sidi Moussa"},
{"scode":"16SMSCRSB","sname":"Cité Rais","nbl":"4","stype":"bus","cid":"1637","cname":"Sidi Moussa"},
{"scode":"16SMSCTRB","sname":"Sidi Moussa (Centre)","nbl":"6","stype":"bus","cid":"1637","cname":"Sidi Moussa"},
{"scode":"16SMSHOUB","sname":"Cité Houaoura","nbl":"6","stype":"bus","cid":"1637","cname":"Sidi Moussa"},
{"scode":"16SMSNMIB","sname":"Domaine Naïmi","nbl":"2","stype":"bus","cid":"1637","cname":"Sidi Moussa"},
{"scode":"16SMSRNDB","sname":"Domaine Ronda","nbl":"4","stype":"bus","cid":"1637","cname":"Sidi Moussa"},
{"scode":"16SMSTFLB","sname":"Cité Gaïd Gacem (Haouch Tafil)","nbl":"2","stype":"bus","cid":"1637","cname":"Sidi Moussa"},
{"scode":"16SMSZOIB","sname":"Cité Zouaoui","nbl":"6","stype":"bus","cid":"1637","cname":"Sidi Moussa"},
{"scode":"16STAAGCB","sname":"Staoueli (Station de bus)","nbl":"12","stype":"bus","cid":"1645","cname":"Staoueli"},
{"scode":"16STAZURB","sname":"Azur Plage","nbl":"6","stype":"bus","cid":"1645","cname":"Staoueli"},
{"scode":"16STBLTAB","sname":"Bellota","nbl":"2","stype":"bus","cid":"1645","cname":"Staoueli"},
{"scode":"16STBOUDB","sname":"C.E.M Fréres Boudouara","nbl":"4","stype":"bus","cid":"1645","cname":"Staoueli"},
{"scode":"16STBRJAB","sname":"El Bridja","nbl":"6","stype":"bus","cid":"1645","cname":"Staoueli"},
{"scode":"16STBRKAB","sname":"Coopérative El-Baraka (Les palmiers)","nbl":"6","stype":"bus","cid":"1645","cname":"Staoueli"},
{"scode":"16STHADJB","sname":"Domaine Hadjeri Ahmed","nbl":"8","stype":"bus","cid":"1645","cname":"Staoueli"},
{"scode":"16STKACIB","sname":"Rue Kaci Ameur","nbl":"2","stype":"bus","cid":"1645","cname":"Staoueli"},
{"scode":"16STMAURB","sname":"Cité Mauriace","nbl":"2","stype":"bus","cid":"1645","cname":"Staoueli"},
{"scode":"16STMIMOB","sname":"Cité Fellag Mohamed (Mimosa)","nbl":"6","stype":"bus","cid":"1645","cname":"Staoueli"},
{"scode":"16STPALMB","sname":"Palm Beach","nbl":"6","stype":"bus","cid":"1645","cname":"Staoueli"},
{"scode":"16STPHTYB","sname":"Polyclinique Phtisiologie","nbl":"4","stype":"bus","cid":"1645","cname":"Staoueli"},
{"scode":"16TAYCTRB","sname":"Aïn Taya (Centre)","nbl":"6","stype":"bus","cid":"1638","cname":"Aïn Taya"},
{"scode":"16ZD1000B","sname":"Cité 1000 Logts \/ Mosquée El-Karia","nbl":"2","stype":"bus","cid":"1646","cname":"Zeralda"},
{"scode":"16ZDADOUB","sname":"Primaire Allal DOUADI","nbl":"2","stype":"bus","cid":"1646","cname":"Zeralda"},
{"scode":"16ZDCCHRB","sname":"Zeralda Cimetière Chrétien","nbl":"1","stype":"bus","cid":"1646","cname":"Zeralda"},
{"scode":"16ZDCMILB","sname":"Zeralda Cité Militaire","nbl":"9","stype":"bus","cid":"1646","cname":"Zeralda"},
{"scode":"16ZDCYNEB","sname":"Centre cynégénétique Zeralda","nbl":"10","stype":"bus","cid":"1647","cname":"Mahelma"},
{"scode":"16ZDDAOUB","sname":"Résidence Ed-daouia","nbl":"2","stype":"bus","cid":"1646","cname":"Zeralda"},
{"scode":"16ZDDKHLB","sname":"Domaine Kheloufi","nbl":"2","stype":"bus","cid":"1646","cname":"Zeralda"},
{"scode":"16ZDHZD1B","sname":"Hôpital de Zeralda","nbl":"3","stype":"bus","cid":"1646","cname":"Zeralda"},
{"scode":"16ZDKRIAB","sname":"El-Karia de Zeralda","nbl":"4","stype":"bus","cid":"1646","cname":"Zeralda"},
{"scode":"16ZDMMARB","sname":"C.E.M Mustapha Marzouk","nbl":"2","stype":"bus","cid":"1646","cname":"Zeralda"},
{"scode":"16ZDNAJDB","sname":"Cité En-Najd (Plateau)","nbl":"2","stype":"bus","cid":"1646","cname":"Zeralda"},
{"scode":"16ZDPCIVB","sname":"Zeralda Protection civile","nbl":"8","stype":"bus","cid":"1646","cname":"Zeralda"},
{"scode":"16ZDPFAMB","sname":"Plage familiale","nbl":"4","stype":"bus","cid":"1646","cname":"Zeralda"},
{"scode":"16ZDPONTB","sname":"Entrée Zeralda - Pont -","nbl":"4","stype":"bus","cid":"1646","cname":"Zeralda"},
{"scode":"16ZDSMCLB","sname":"Sidi Menif - Polyclinique -","nbl":"4","stype":"bus","cid":"1646","cname":"Zeralda"},
{"scode":"16ZDSMCMB","sname":"Sidi Menif - Cimetiére -","nbl":"4","stype":"bus","cid":"1646","cname":"Zeralda"},
{"scode":"16ZDSMM1B","sname":"Zeralda Station M.M","nbl":"3","stype":"bus","cid":"1646","cname":"Zeralda"},
{"scode":"16ZDSMPNB","sname":"Entrée Sidi Menif - Pont -","nbl":"2","stype":"bus","cid":"1646","cname":"Zeralda"},
{"scode":"16ZDTOURB","sname":"Zeralda - Complexe touristique -","nbl":"16","stype":"bus","cid":"1646","cname":"Zeralda"},
{"scode":"16ZDVARTB","sname":"Village des artistes","nbl":"2","stype":"bus","cid":"1646","cname":"Zeralda"},
{"scode":"16ZERALDB","sname":"Zeralda (Station de bus)","nbl":"27","stype":"bus","cid":"1646","cname":"Zeralda"},
{"scode":"35HMDAGCB","sname":"Hammadi (Station de bus)","nbl":"6","stype":"bus","cid":"3536","cname":"Hammedi"},
{"scode":"35HMDBLHB","sname":"Ouled Belhadi","nbl":"2","stype":"bus","cid":"3536","cname":"Hammedi"},
{"scode":"35HMDBMRB","sname":"Hammadi (Ben Amar)","nbl":"4","stype":"bus","cid":"3536","cname":"Hammedi"},
{"scode":"35HMDMDSB","sname":"Hammadi (Mouaïcia)","nbl":"4","stype":"bus","cid":"3536","cname":"Hammedi"}]}
